constants.py
covert.py
covert_ots-1.0.8.dist-info/METADATA
covert_ots-1.0.8.dist-info/WHEEL
covert_ots-1.0.8.dist-info/entry_points.txt
covert_ots-1.0.8.dist-info/top_level.txt
covert_ots-1.0.8.dist-info/RECORD
