Metadata-Version: 2.1
Name: covert-ots
Version: 1.0.8
Summary: A secure way to communicate your secrets
Home-page: UNKNOWN
Author: Om Gupta
License: UNKNOWN
Platform: UNKNOWN
Classifier: Programming Language :: Python :: 3
Classifier: License :: OSI Approved :: MIT License
Classifier: Operating System :: OS Independent
Requires-Python: >=3.6
Requires-Dist: inquirer
Requires-Dist: pycryptodome
Requires-Dist: rich
Requires-Dist: typer
